{
  "name": "@ifiokjr/oh-pi-themes",
  "latest_version": "0.2.2",
  "description": "Color themes for pi: cyberpunk, nord, gruvbox, tokyo-night, catppuccin, and more.",
  "readme": "ERROR: No README data found!",
  "keywords": [
    "pi-package"
  ],
  "author": null,
  "license": "MIT",
  "homepage": null,
  "repository": null,
  "pi": {
    "themes": [
      "./themes"
    ]
  },
  "time": {
    "created": "2026-03-08T09:09:19.309Z",
    "0.2.2": "2026-03-08T09:09:19.569Z",
    "modified": "2026-03-08T09:09:19.838Z"
  },
  "versions_count": 1,
  "downloads_last_week": 8,
  "download_trend": []
}