{
  "name": "@nonplanarslicer/pi-save-output",
  "latest_version": "1.0.3",
  "description": "Save the last assistant message to a markdown file via /save-output",
  "readme": "# pi-save-output\n\nA pi extension that saves the last assistant message to a markdown file.\n\nWhen you see something you like \u2014 a nice bit of output, a summary you want to keep \u2014 the old way was to ask the model to write it to a file for you. That works, but it burns tokens and pollutes the model context just to shuffle text around. This extension side-steps all of that. It takes the last assistant message straight from the session and writes it to disk. No round-trip through the model, no context noise, just done.\n\n## Usage\n\n```\n/save-output <path/to/file.md>\n```\n\nWhen you run the command, it scans the session history in reverse to find the most recent assistant message, extracts the text from it, and writes that text to the file you specified. Parent directories are created automatically if they don't exist. If the file already exists, you'll be prompted to confirm overwriting it before anything is written.\n\nNon-text content (tool calls, images, etc.) is stripped out \u2014 only the actual written response ends up in the file.\n\n## Install\n\n```bash\npi install npm:@nonplanarslicer/pi-save-output\n```\n\nOr run it without installing:\n\n```bash\npi -e ./index.ts\n```\n",
  "keywords": [
    "pi-package"
  ],
  "author": null,
  "license": null,
  "homepage": "https://github.com/christophacham/pi-save-output#readme",
  "repository": {
    "type": "git",
    "url": "git+https://github.com/christophacham/pi-save-output.git"
  },
  "pi": {
    "extensions": [
      "./index.ts"
    ]
  },
  "time": {
    "created": "2026-04-29T18:11:43.662Z",
    "modified": "2026-04-29T18:19:28.181Z",
    "1.0.1": "2026-04-29T18:11:43.965Z",
    "1.0.2": "2026-04-29T18:16:59.210Z",
    "1.0.3": "2026-04-29T18:19:28.073Z"
  },
  "versions_count": 3,
  "downloads_last_week": null,
  "download_trend": []
}