{
  "name": "pi-repoprompt-tools-lock",
  "latest_version": "0.1.4",
  "description": "Forces the agent to use RepoPrompt tools during repo-scoped work by disabling Pi's native tools when RepoPrompt tools are available (through either the `pi-repoprompt-cli` or `pi-repoprompt-mcp` Pi packages/extensions)",
  "readme": "# RepoPrompt tools lock for Pi (`pi-repoprompt-tools-lock`)\n\nForces the agent to use RepoPrompt tools during repo-scoped work by disabling Pi's native tools `read`, `write`, `edit`, `ls`, `find`, `grep` when RepoPrompt tools are available (through either the `pi-repoprompt-cli` or `pi-repoprompt-mcp` Pi packages/extensions).\n\n## Install\n\nFrom npm:\n\n```bash\npi install npm:pi-repoprompt-tools-lock\n```\n\nFrom the dot314 git bundle (filtered install):\n\nAdd to `~/.pi/agent/settings.json` (or replace an existing unfiltered `git:github.com/w-winter/dot314` entry):\n\n```json\n{\n  \"packages\": [\n    {\n      \"source\": \"git:github.com/w-winter/dot314\",\n      \"extensions\": [\"extensions/rp-native-tools-lock/index.ts\"],\n      \"skills\": [],\n      \"themes\": [],\n      \"prompts\": []\n    }\n  ]\n}\n```\n\n## Usage\n\n- Command: `/rp-tools-lock off|auto`\n- Shortcut: `Alt+L` (toggles `off` \u2194 `auto`)\n\nIn `auto` mode, the lock is enforced only when one of these tools is active:\n- `rp` (RepoPrompt MCP)\n- `rp_exec` (RepoPrompt CLI)\n\nWhen enforced, the footer shows: `RP \ud83d\udd12`.\n\n## Configuration (advanced)\n\nAdvanced modes can be set via:\n\n- `~/.pi/agent/extensions/rp-native-tools-lock/rp-native-tools-lock.json`\n\nExample:\n\n```json\n{ \"mode\": \"rp-mcp\" }\n```\n",
  "keywords": [
    "pi-package",
    "pi",
    "pi-coding-agent",
    "repoprompt"
  ],
  "author": null,
  "license": "MIT",
  "homepage": "https://github.com/w-winter/dot314#readme",
  "repository": {
    "type": "git",
    "url": "git+https://github.com/w-winter/dot314.git",
    "directory": "packages/pi-repoprompt-tools-lock"
  },
  "pi": {
    "extensions": [
      "extensions/rp-native-tools-lock/index.ts"
    ]
  },
  "time": {
    "created": "2026-01-28T01:45:36.290Z",
    "modified": "2026-05-07T17:06:26.917Z",
    "0.1.0": "2026-01-28T01:45:36.440Z",
    "0.1.1": "2026-03-31T15:25:38.154Z",
    "0.1.2": "2026-04-03T21:21:14.924Z",
    "0.1.3": "2026-04-05T18:37:14.025Z",
    "0.1.4": "2026-05-07T17:06:26.802Z"
  },
  "versions_count": 5,
  "downloads_last_week": null,
  "download_trend": []
}